fastapi_lazy/__init__.py
fastapi_lazy/auth/__init__.py
fastapi_lazy/auth/auth.py
fastapi_lazy/auth/token.py
fastapi_lazy/database/__init__.py
fastapi_lazy/database/mongo.py
fastapi_lazy/database/psql.py
fastapi_lazy/database/redis.py
fastapi_lazy/database/sqlite.py
fastapi_lazy/generator/__init__.py
fastapi_lazy/generator/crud.py
fastapi_lazy/generator/generator.py
fastapi_lazy/generator/token_provider.py
fastapi_lazy/graphQL/__init__.py
fastapi_lazy/models/__init__.py
fastapi_lazy/models/models.py
fastapi_lazy/utils/__init__.py
fastapi_lazy/utils/hash.py
fastapi_lazy/utils/validator.py
fastapi_lazy-1.2.6.dist-info/LICENSE
fastapi_lazy-1.2.6.dist-info/METADATA
fastapi_lazy-1.2.6.dist-info/WHEEL
fastapi_lazy-1.2.6.dist-info/top_level.txt
fastapi_lazy-1.2.6.dist-info/RECORD
