Metadata-Version: 2.1
Name: fastapi-lazy
Version: 1.2.6
Summary: Utilities that you use in various projects made in FastAPI
Home-page: https://github.com/yezz123/fastapi-lazy
Author: Yasser Tahiri
Author-email: yasserth19@gmail.com
License: UNKNOWN
Platform: UNKNOWN
Classifier: License :: OSI Approved :: MIT License
Classifier: Operating System :: OS Independent
Classifier: Intended Audience :: Developers
Classifier: Framework :: FastAPI
Classifier: Programming Language :: Python :: 3.7
Classifier: Programming Language :: Python :: 3.8
Classifier: Programming Language :: Python :: 3.9
Classifier: Programming Language :: Python :: 3.10
Classifier: Programming Language :: Python :: 3 :: Only
Classifier: Topic :: Internet :: WWW/HTTP :: Session
Requires-Python: >=3.7
License-File: LICENSE
Requires-Dist: fastapi
Requires-Dist: databases
Requires-Dist: motor
Requires-Dist: pyjwt
Requires-Dist: aioredis (==2.0.0)
Requires-Dist: email-validator
Requires-Dist: passlib
